ananke_sdk
