Metadata-Version: 1.0
Name: ananke-sdk
Version: 1.1.2
Summary: This is SDK is used to connect devices to Ananke IoT platform
Home-page: https://github.com/ferrumaeternum/ananke_sdk
Author: Effective Solutions Ltd,Sri Lanka
Author-email: bathiyathennakoon@outlook.com
License: MIT
Platform: UNKNOWN
